README.md
setup.py
scripts/tinder-cli
scripts/tinder-cli.py
tinder_cli/__init__.py
tinder_cli/cli.py
tinder_cli/client.py
tinder_cli.egg-info/PKG-INFO
tinder_cli.egg-info/SOURCES.txt
tinder_cli.egg-info/dependency_links.txt
tinder_cli.egg-info/requires.txt
tinder_cli.egg-info/top_level.txt