Metadata-Version: 1.2
Name: tinder-cli
Version: 1.2.0
Summary: Tinder for terminal junkies
Home-page: https://github.com/meister245/tinder-cli
Author: Zsolt Mester
Author-email: 
License: MIT
Project-URL: Code, https://github.com/meister245/tinder-cli
Project-URL: Issue tracker, https://github.com/meister245/tinder-cli/issues
Platform: UNKNOWN
Requires-Python: >=3.6
